pyseries/__init__.py
pyseries/Analysis/Anova.py
pyseries/Analysis/CrossCorrelate.py
pyseries/Analysis/Explore.py
pyseries/Analysis/Normalize.py
pyseries/Analysis/Trends.py
pyseries/Analysis/__init__.py
pyseries/LoadingData/Read_edf.py
pyseries/LoadingData/Read_mat.py
pyseries/LoadingData/__init__.py
pyseries/Pipelines/AnalyzeBinRIv.py
pyseries/Pipelines/AnalyzeRest.py
pyseries/Pipelines/AnalyzeSsvep.py
pyseries/Pipelines/__init__.py
pyseries/Preprocessing/ArtifactRemoval.py
pyseries/Preprocessing/Epochs.py
pyseries/Preprocessing/PrepareData.py
pyseries/Preprocessing/__init__.py
pyseries-1.0.26.dist-info/DESCRIPTION.rst
pyseries-1.0.26.dist-info/METADATA
pyseries-1.0.26.dist-info/RECORD
pyseries-1.0.26.dist-info/WHEEL
pyseries-1.0.26.dist-info/metadata.json
pyseries-1.0.26.dist-info/top_level.txt
