Metadata-Version: 2.0
Name: pyseries
Version: 1.0.26
Summary: pySeries is a package for statistical analysis of time-series data.
Home-page: http://pyseries.readthedocs.io/en/latest/
Author: Ryszard Cetnarski
Author-email: cetnarski.ryszard@gmail.com
License: MIT
Keywords: time,series,signal,analysis,statistics
Platform: UNKNOWN
Classifier: Development Status :: 1 - Planning
Classifier: Topic :: Scientific/Engineering :: Bio-Informatics
Classifier: License :: OSI Approved :: BSD License
Classifier: Intended Audience :: Science/Research
Requires-Dist: deepdish
Requires-Dist: matplotlib
Requires-Dist: numpy
Requires-Dist: obspy
Requires-Dist: pandas
Requires-Dist: pyedflib
Requires-Dist: scipy
Requires-Dist: seaborn
Requires-Dist: sklearn
Requires-Dist: tabulate
